reahl/webdev/__init__.py
reahl/webdev/commands.py
reahl/webdev/fixtures.py
reahl/webdev/reahl_development_cert.pem
reahl/webdev/webserver.py
reahl/webdev_dev/__init__.py
reahl/webdev_dev/test_create_app.py
reahl/webdev_dev/test_webserver.py
reahl/webdev_dev/web_server_wsgi_application_details.puml
reahl_webdev-7.0.3.dist-info/LICENSE
reahl_webdev-7.0.3.dist-info/METADATA
reahl_webdev-7.0.3.dist-info/WHEEL
reahl_webdev-7.0.3.dist-info/entry_points.txt
reahl_webdev-7.0.3.dist-info/reahl-component.toml
reahl_webdev-7.0.3.dist-info/top_level.txt
reahl_webdev-7.0.3.dist-info/RECORD
